datafactory/__init__.py
datafactory/compat.py
datafactory/exceptions.py
datafactory/api/__init__.py
datafactory/api/display.py
datafactory/api/render.py
datafactory/api/special.py
datafactory/containers/__init__.py
datafactory/containers/base.py
datafactory/containers/dict.py
datafactory/containers/iter.py
datafactory/containers/list.py
datafactory/fields/__init__.py
datafactory/fields/base.py
datafactory/fields/choice.py
datafactory/fields/cycle.py
datafactory/fields/hashof.py
datafactory/fields/increment.py
datafactory/fields/pickout.py
datafactory/fields/sequence.py
datafactory/formatters/__init__.py
datafactory/formatters/base.py
datafactory/formatters/csv.py
datafactory/formatters/json.py
datafactory/formatters/pickle.py
datafactory/formatters/string.py
datafactory/models/__init__.py
datafactory/models/base.py
datafactory/models/dict.py
datafactory/models/list.py
datafactory/utils/__init__.py
datafactory/utils/datetime.py
tests/containers/__init__.py
tests/containers/test_base.py
tests/containers/test_dict.py
tests/containers/test_iter.py
tests/containers/test_list.py
tests/fields/__init__.py
tests/fields/test_choice.py
tests/fields/test_cycle.py
tests/fields/test_hashof.py
tests/fields/test_increment.py
tests/fields/test_pickout.py
tests/fields/test_sequence.py
tests/formatters/__init__.py
tests/formatters/test_base.py
tests/formatters/test_csv.py
tests/formatters/test_json.py
tests/formatters/test_pickle.py
tests/formatters/test_string.py
tests/models/__init__.py
tests/models/test_dict.py
tests/models/test_list.py
tests/utils/__init__.py
tests/utils/test_datetime.py
datafactory-1.0.1.dist-info/LICENSE
datafactory-1.0.1.dist-info/METADATA
datafactory-1.0.1.dist-info/WHEEL
datafactory-1.0.1.dist-info/top_level.txt
datafactory-1.0.1.dist-info/RECORD
