Metadata-Version: 2.1
Name: datafactory
Version: 1.0.1
Summary: datafactory generates testdata.
Home-page: https://github.com/walkframe/datafactory
Author: righ
Author-email: righ.m9@gmail.com
License: Apache License 2.0
Keywords: testdata,datafactory,fixtures,dummydata,daterange
Platform: UNKNOWN
Classifier: Intended Audience :: Developers
Classifier: License :: OSI Approved :: Apache Software License
Classifier: Programming Language :: Python
Classifier: Topic :: Software Development
